setup.cfg
setup.py
SMSProvider.egg-info/PKG-INFO
SMSProvider.egg-info/SOURCES.txt
SMSProvider.egg-info/dependency_links.txt
SMSProvider.egg-info/requires.txt
SMSProvider.egg-info/top_level.txt
smsprovider/DeviceSMSProvider.py
smsprovider/FileSMSProvider.py
smsprovider/HttpSMSProvider.py
smsprovider/SMPPSMSProvider.py
smsprovider/SMSProvider.py
smsprovider/SmtpSMSProvider.py
smsprovider/TestSMSProvider.py
smsprovider/__init__.py
test/test_devicesms.py
test/test_sms.py