Metadata-Version: 1.0
Name: SMSProvider
Version: 2.9.0.3
Summary: LinOTP2 modules for submitting SMS messages
Home-page: http://www.linotp.org
Author: KeyIdentity GmbH
Author-email: linotp@lsexperts.de
License: AGPLv3, (C) KeyIdentity GmbH
Keywords: OTP LinOTP2 SMS
Platform: UNKNOWN
